trl/__init__.py
trl/_compat.py
trl/chat_template_utils.py
trl/cli.py
trl/data_utils.py
trl/import_utils.py
trl/mergekit_utils.py
trl/py.typed
trl/accelerate_configs/fsdp1.yaml
trl/accelerate_configs/fsdp2.yaml
trl/accelerate_configs/multi_gpu.yaml
trl/accelerate_configs/single_gpu.yaml
trl/accelerate_configs/zero1.yaml
trl/accelerate_configs/zero2.yaml
trl/accelerate_configs/zero3.yaml
trl/experimental/__init__.py
trl/experimental/merge_model_callback.py
trl/experimental/utils.py
trl/experimental/winrate_callback.py
trl/experimental/bco/__init__.py
trl/experimental/bco/bco_config.py
trl/experimental/bco/bco_trainer.py
trl/experimental/bema_for_ref_model/__init__.py
trl/experimental/bema_for_ref_model/callback.py
trl/experimental/bema_for_ref_model/dpo_trainer.py
trl/experimental/cpo/__init__.py
trl/experimental/cpo/cpo_config.py
trl/experimental/cpo/cpo_trainer.py
trl/experimental/gfpo/__init__.py
trl/experimental/gfpo/gfpo_config.py
trl/experimental/gfpo/gfpo_trainer.py
trl/experimental/gkd/__init__.py
trl/experimental/gkd/gkd_config.py
trl/experimental/gkd/gkd_trainer.py
trl/experimental/gold/__init__.py
trl/experimental/gold/gold.py
trl/experimental/gold/gold_config.py
trl/experimental/gold/gold_trainer.py
trl/experimental/grpo_with_replay_buffer/__init__.py
trl/experimental/grpo_with_replay_buffer/grpo_with_replay_buffer_config.py
trl/experimental/grpo_with_replay_buffer/grpo_with_replay_buffer_trainer.py
trl/experimental/gspo_token/__init__.py
trl/experimental/gspo_token/grpo_trainer.py
trl/experimental/judges/__init__.py
trl/experimental/judges/judges.py
trl/experimental/kto/__init__.py
trl/experimental/kto/kto_config.py
trl/experimental/kto/kto_trainer.py
trl/experimental/minillm/__init__.py
trl/experimental/minillm/minillm_config.py
trl/experimental/minillm/minillm_trainer.py
trl/experimental/nash_md/__init__.py
trl/experimental/nash_md/nash_md_config.py
trl/experimental/nash_md/nash_md_trainer.py
trl/experimental/online_dpo/__init__.py
trl-0.27.1.dist-info/licenses/LICENSE
trl-0.27.1.dist-info/METADATA
trl-0.27.1.dist-info/WHEEL
trl-0.27.1.dist-info/entry_points.txt
trl-0.27.1.dist-info/top_level.txt
trl-0.27.1.dist-info/RECORD
