Metadata-Version: 2.4
Name: trl
Version: 0.27.1
Summary: Train transformer language models with reinforcement learning.
Author-email: Leandro von Werra <leandro.vonwerra@gmail.com>
License-Expression: Apache-2.0
Project-URL: Homepage, https://github.com/huggingface/trl
Keywords: transformers,huggingface,language modeling,post-training,rlhf,sft,dpo,grpo
Classifier: Development Status :: 2 - Pre-Alpha
Classifier: Intended Audience :: Developers
Classifier: Intended Audience :: Science/Research
Classifier: Natural Language :: English
Classifier: Operating System :: OS Independent
Classifier: Programming Language :: Python :: 3
Classifier: Programming Language :: Python :: 3.10
Classifier: Programming Language :: Python :: 3.11
Classifier: Programming Language :: Python :: 3.12
Classifier: Programming Language :: Python :: 3.13
Requires-Python: >=3.10
License-File: LICENSE
Requires-Dist: accelerate>=1.4.0
Requires-Dist: datasets>=3.0.0
Requires-Dist: packaging>20.0
Requires-Dist: transformers>=4.56.2
Provides-Extra: bco
Requires-Dist: scikit-learn; extra == "bco"
Requires-Dist: joblib; extra == "bco"
Provides-Extra: deepspeed
Requires-Dist: deepspeed>=0.14.4; extra == "deepspeed"
Provides-Extra: judges
Requires-Dist: openai>=1.23.2; extra == "judges"
Requires-Dist: llm-blender>=0.0.2; extra == "judges"
Provides-Extra: kernels
Requires-Dist: kernels; extra == "kernels"
Provides-Extra: liger
Requires-Dist: liger-kernel>=0.6.4; extra == "liger"
Provides-Extra: peft
Requires-Dist: peft>=0.8.0; extra == "peft"
Provides-Extra: quality
Requires-Dist: pre-commit; extra == "quality"
Requires-Dist: hf-doc-builder; extra == "quality"
Provides-Extra: quantization
Requires-Dist: bitsandbytes; extra == "quantization"
Provides-Extra: scikit
Requires-Dist: scikit-learn; extra == "scikit"
Provides-Extra: test
Requires-Dist: pytest-cov; extra == "test"
Requires-Dist: pytest-rerunfailures==15.1; extra == "test"
Requires-Dist: pytest-xdist; extra == "test"
Requires-Dist: pytest; extra == "test"
Provides-Extra: vllm
Requires-Dist: vllm<0.13.0,>=0.10.2; extra == "vllm"
Requires-Dist: fastapi; extra == "vllm"
Requires-Dist: pydantic; extra == "vllm"
Requires-Dist: requests; extra == "vllm"
Requires-Dist: uvicorn; extra == "vllm"
Provides-Extra: vlm
Requires-Dist: Pillow; extra == "vlm"
Requires-Dist: torchvision; extra == "vlm"
Requires-Dist: num2words==0.5.14; extra == "vlm"
Provides-Extra: math-verify
Requires-Dist: math-verify>=0.5.2; extra == "math-verify"
Provides-Extra: dev
Requires-Dist: scikit-learn; extra == "dev"
Requires-Dist: joblib; extra == "dev"
Requires-Dist: deepspeed>=0.14.4; extra == "dev"
Requires-Dist: openai>=1.23.2; extra == "dev"
Requires-Dist: llm-blender>=0.0.2; extra == "dev"
Requires-Dist: kernels; extra == "dev"
Requires-Dist: liger-kernel>=0.6.4; extra == "dev"
Requires-Dist: peft>=0.8.0; extra == "dev"
Requires-Dist: pre-commit; extra == "dev"
Requires-Dist: hf-doc-builder; extra == "dev"
Requires-Dist: bitsandbytes; extra == "dev"
Requires-Dist: pytest-cov; extra == "dev"
Requires-Dist: pytest-rerunfailures==15.1; extra == "dev"
Requires-Dist: pytest-xdist; extra == "dev"
Requires-Dist: pytest; extra == "dev"
Requires-Dist: Pillow; extra == "dev"
Requires-Dist: torchvision; extra == "dev"
Requires-Dist: num2words==0.5.14; extra == "dev"
Requires-Dist: jmespath; extra == "dev"
Dynamic: license-file
